COPYING
COPYING.LESSER
COPYING.orig
MANIFEST.in
setup.py
moretools/__init__.py
moretools/_caller.py
moretools/_collections.py
moretools/_common.py
moretools/_del.py
moretools/_empty.py
moretools/_filter.py
moretools/_get.py
moretools/_has.py
moretools/_map.py
moretools/_multi.py
moretools/_multidict.py
moretools/_multisimpledict.py
moretools/_pkg.py
moretools/_query.py
moretools/_repeat.py
moretools/_set.py
moretools/_simpledict.py
moretools/_star.py
moretools/_string.py
python_moretools.egg-info/PKG-INFO
python_moretools.egg-info/SOURCES.txt
python_moretools.egg-info/dependency_links.txt
python_moretools.egg-info/top_level.txt