Metadata-Version: 1.1
Name: python-moretools
Version: 0.1a25
Summary: [Obsolete] Renamed to https://pypi.python.org/pypi/moretools : Many more basic tools for python 2/3 extending itertools, functools, operator and collections.
Home-page: http://bitbucket.org/userzimmermann/python-moretools
Author: Stefan Zimmermann
Author-email: zimmermann.code@gmail.com
License: LGPLv3
Keywords: tools,itertools,functools,operator,collections,iterator,iteration,functional,filter,map,repeat,query,tuple,list,set,dict,simpledict,camelize,decamelize,python3
Platform: UNKNOWN
Classifier: Development Status :: 3 - Alpha
Classifier: Intended Audience :: Developers
Classifier: License :: OSI Approved :: GNU Library or Lesser General Public License (LGPL)
Classifier: Operating System :: OS Independent
Classifier: Programming Language :: Python :: 2
Classifier: Programming Language :: Python :: 3
Classifier: Topic :: Software Development
Classifier: Topic :: Utilities
